geosci/__init__.py
geosci/common.py
geosci/geosci.py
geosci/utils.py
geosci-0.0.4.dist-info/LICENSE
geosci-0.0.4.dist-info/METADATA
geosci-0.0.4.dist-info/WHEEL
geosci-0.0.4.dist-info/dependency_links.txt
geosci-0.0.4.dist-info/top_level.txt
geosci-0.0.4.dist-info/RECORD
