Metadata-Version: 2.1
Name: geosci
Version: 0.0.4
Summary: A Python package for interactive mapping
Home-page: https://github.com/coliaxu/geosci
Author: Haixia Xu
Author-email: coliaxu@gmail.com
License: MIT license
Keywords: geosci
Platform: UNKNOWN
Classifier: Development Status :: 2 - Pre-Alpha
Classifier: Intended Audience :: Developers
Classifier: License :: OSI Approved :: MIT License
Classifier: Natural Language :: English
Classifier: Programming Language :: Python :: 3
Classifier: Programming Language :: Python :: 3.5
Classifier: Programming Language :: Python :: 3.6
Classifier: Programming Language :: Python :: 3.7
Classifier: Programming Language :: Python :: 3.8
Requires-Python: >=3.5
Requires-Dist: earthengine-api
Requires-Dist: folium
Requires-Dist: ipyleaflet
Requires-Dist: pyshp
